{"is_source_file": true, "format": "TypeScript/TSX", "description": "This file defines a React component 'RemotionRoot' that sets up multiple media compositions for a project using the Remotion library. It imports components and schemas and configures compositions with specific properties, serving as an entry point for rendering videos.", "external_files": ["./HelloWorld", "./HelloWorld/Logo"], "external_methods": ["remotion.Composition", "React.FC"], "published": [], "classes": [], "methods": [{"name": "RemotionRoot", "description": "React functional component that creates a root container with multiple 'Composition' entries for video rendering."}], "calls": ["remotion.Composition", "React.createElement"], "search-terms": ["RemotionRoot", "Composition", "HelloWorld", "Logo", "React.FC", "video compositions", "src/Root.tsx"], "state": 2, "file_id": 11, "knowledge_revision": 30, "git_revision": "72cd719f2e98e8e5fbffa9bbdbaf4ba23669fc2e", "ctags": [], "hash": "e7dd365e19e3e2c921953e942d5e0cad", "format-version": 4, "code-base-name": "todo_frontend", "filename": "todo_frontend/src/Root.tsx", "revision_history": [{"30": "72cd719f2e98e8e5fbffa9bbdbaf4ba23669fc2e"}]}